arcadia_pycolor/__init__.py
arcadia_pycolor/colors.py
arcadia_pycolor/cvd.py
arcadia_pycolor/display.py
arcadia_pycolor/gradient.py
arcadia_pycolor/gradients.py
arcadia_pycolor/hexcode.py
arcadia_pycolor/mpl.py
arcadia_pycolor/palette.py
arcadia_pycolor/palettes.py
arcadia_pycolor/plot.py
arcadia_pycolor/plotly_utils.py
arcadia_pycolor/style_defaults.py
arcadia_pycolor/tests/__init__.py
arcadia_pycolor/tests/plotting/test_3d_plots.py
arcadia_pycolor/tests/plotting/test_barplots.py
arcadia_pycolor/tests/plotting/test_bespoke_plots.py
arcadia_pycolor/tests/plotting/test_seaborn_plots.py
arcadia_pycolor/tests/test_gradients.py
arcadia_pycolor/tests/test_hexcode.py
arcadia_pycolor/tests/test_import.py
arcadia_pycolor/tests/test_mpl_conversions.py
arcadia_pycolor/tests/test_mpl_save_figure.py
arcadia_pycolor/tests/test_mpl_setup.py
arcadia_pycolor/tests/test_palette.py
arcadia_pycolor/tests/test_plotly_save_figure.py
arcadia_pycolor/tests/test_plotly_setup.py
arcadia_pycolor/tests/test_utils.py
arcadia_pycolor/utils.py
arcadia_pycolor-0.6.5.dist-info/LICENSE
arcadia_pycolor-0.6.5.dist-info/METADATA
arcadia_pycolor-0.6.5.dist-info/WHEEL
arcadia_pycolor-0.6.5.dist-info/RECORD
