Metadata-Version: 2.1
Name: arcadia-pycolor
Version: 0.6.5
Summary: A Python package to distribute Arcadia's color and style guidelines for figures.
Home-page: https://github.com/Arcadia-Science/arcadia-pycolor
License: MIT
Author: Keith Cheveralls
Author-email: keith.cheveralls@arcadiascience.com
Requires-Python: >=3.9,<4.0
Classifier: License :: OSI Approved :: MIT License
Classifier: Programming Language :: Python :: 3
Classifier: Programming Language :: Python :: 3.9
Classifier: Programming Language :: Python :: 3.10
Classifier: Programming Language :: Python :: 3.11
Classifier: Programming Language :: Python :: 3.12
Requires-Dist: beautifulsoup4 (>=4.13.4,<5.0.0)
Requires-Dist: colorspacious (>=1.1.2)
Requires-Dist: kaleido (==0.2.1)
Requires-Dist: matplotlib (>=3.7,!=3.8.0)
Requires-Dist: numpy (>=1.20)
Requires-Dist: plotly (>=6.0.0)
Project-URL: Documentation, https://github.com/Arcadia-Science/arcadia-pycolor
Project-URL: Repository, https://github.com/Arcadia-Science/arcadia-pycolor
